<RT>
    <camera>
        <look_from>
            <x>0.0</x>
            <y>0.0</y>
            <z>25.0</z>
        </look_from>
        <look_at>
            <x>0.0</x>
            <y>0.0</y>
            <z>0.0</z>
        </look_at>
        <scene_type>normal</scene_type>
        <algo_type>simple</algo_type>
    </camera>
    <light>
        <position>
            <x>0.0</x>
            <y>10.0</y>
            <z>0.0</z>
        </position>
        <color>
            <x>255</x>
            <y>255</y>
            <z>255</z>
        </color>
        <intensity>
            <x>0.7</x>
            <y>0.7</y>
            <z>0.7</z>
        </intensity>
        <ambient>0.05</ambient>
    </light>
    <light>
        <position>
            <x>3.0</x>
            <y>5.0</y>
            <z>8.0</z>
        </position>
        <color>
            <x>255</x>
            <y>255</y>
            <z>255</z>
        </color>
        <intensity>
            <x>0.7</x>
            <y>0.7</y>
            <z>0.7</z>
        </intensity>
        <ambient>0.05</ambient>
    </light>
    <plane>
        <position>
            <x>0.0</x>
            <y>-3.0</y>
            <z>0.0</z>
        </position>
        <axis>
            <x>0.0</x>
            <y>1.0</y>
            <z>0.0</z>
        </axis>
        <color>
            <x>49</x>
            <y>50</y>
            <z>111</z>
        </color>
        <translation>
            <x>90</x>
            <y>0</y>
            <z>0</z>
        </translation>
        <diffuse>1</diffuse>
    </plane>
    <cube>
        <position>
            <x>0</x>
            <y>0</y>
            <z>0</z>
        </position>
        <radius>10</radius>
        <color>
            <x>255</x>
            <y>255</y>
            <z>51</z>
        </color>
        <diffuse>1</diffuse>
        <specular>1</specular>
    </cube>
</RT>
